component_injector/__init__.py
component_injector-1.1.1.dist-info/WHEEL
component_injector-1.1.1.dist-info/METADATA
component_injector-1.1.1.dist-info/RECORD
